celltypist/__init__.py
celltypist/annotate.py
celltypist/classifier.py
celltypist/command_line.py
celltypist/logger.py
celltypist/models.py
celltypist/plot.py
celltypist/samples.py
celltypist/train.py
celltypist/data/samples/Ensembl105_Human2Mouse_Genes.csv
celltypist/data/samples/Ensembl110_Cynomolgus2Mouse_Genes.csv
celltypist/data/samples/Ensembl110_Cynomolgus2Pig_Genes.csv
celltypist/data/samples/Ensembl110_Cynomolgus2Rhesus_Genes.csv
celltypist/data/samples/Ensembl110_Human2Cynomolgus_Genes.csv
celltypist/data/samples/Ensembl110_Human2Pig_Genes.csv
celltypist/data/samples/Ensembl110_Human2Rhesus_Genes.csv
celltypist/data/samples/Ensembl110_Pig2Mouse_Genes.csv
celltypist/data/samples/Ensembl110_Rhesus2Mouse_Genes.csv
celltypist/data/samples/Ensembl110_Rhesus2Pig_Genes.csv
celltypist/data/samples/GENCODEv44_Gene_id2name.csv
celltypist/data/samples/sample_cell_by_gene.csv
celltypist_SO-1.6.5.dist-info/LICENSE
celltypist_SO-1.6.5.dist-info/METADATA
celltypist_SO-1.6.5.dist-info/WHEEL
celltypist_SO-1.6.5.dist-info/entry_points.txt
celltypist_SO-1.6.5.dist-info/top_level.txt
celltypist_SO-1.6.5.dist-info/RECORD
