Metadata-Version: 2.1
Name: celltypist-SO
Version: 1.6.5
Summary: A tool for semi-automatic cell type classification. This is a fork that removes leidenalg from the requirements.txt file to remove any GPL dependencies (igraph). All credit goes to original CellTypist authors (Chuan Xu et al.: cx1@sanger.ac.uk)
Home-page: https://github.com/Mena-SA-Kamel/celltypist-SO
Author: Mena Kamel
Author-email: mena.kamel@sanofi.com
Classifier: Programming Language :: Python :: 3
Classifier: Operating System :: OS Independent
Classifier: Intended Audience :: Science/Research
Classifier: Topic :: Scientific/Engineering :: Bio-Informatics
Classifier: Development Status :: 5 - Production/Stable
Requires-Python: >=3.6
License-File: LICENSE
Requires-Dist: numpy>=1.19.0
Requires-Dist: pandas>=1.0.5
Requires-Dist: scikit-learn>=0.24.1
Requires-Dist: openpyxl>=3.0.4
Requires-Dist: click>=7.1.2
Requires-Dist: requests>=2.23.0
Requires-Dist: scanpy>=1.7.0
